scp/__init__.py
scp/base_fluid.py
scp/base_melinder.py
scp/cli.py
scp/ethyl_alcohol.py
scp/ethylene_glycol.py
scp/methyl_alcohol.py
scp/propylene_glycol.py
scp/water.py
secondarycoolantprops-1.3.dist-info/LICENSE
secondarycoolantprops-1.3.dist-info/METADATA
secondarycoolantprops-1.3.dist-info/WHEEL
secondarycoolantprops-1.3.dist-info/entry_points.txt
secondarycoolantprops-1.3.dist-info/RECORD
