Metadata-Version: 2.3
Name: SecondaryCoolantProps
Version: 1.3
Summary: Fluid property routines for secondary coolants based on correlations developed by Åke Melinder, 2010 "Properties of Secondary Working Fluids for Indirect Systems" 2nd ed., International Institute of Refrigeration.
License: BSD-3-Clause
Author: Matt Mitchell
Author-email: mitchute@gmail.com
Requires-Python: >=3.9,<3.14
Classifier: License :: OSI Approved :: BSD License
Classifier: Programming Language :: Python :: 3
Classifier: Programming Language :: Python :: 3.9
Classifier: Programming Language :: Python :: 3.10
Classifier: Programming Language :: Python :: 3.11
Classifier: Programming Language :: Python :: 3.12
Classifier: Programming Language :: Python :: 3.13
Requires-Dist: click (>=8.0,<9.0)
Project-URL: Repository, https://github.com/mitchute/SecondaryCoolantProps
